{
  "d": "[{\"RequestNumber\":\"TRI63893763867093166000\",\"Index Name\":\"Nifty Non-Cyclical Consumer\",\"Date\":\"06 Apr 2005\",\"TotalReturnsIndex\":\"1008.14\"},{\"RequestNumber\":\"TRI63893763867093166000\",\"Index Name\":\"Nifty Non-Cyclical Consumer\",\"Date\":\"05 Apr 2005\",\"TotalReturnsIndex\":\"993.09\"},{\"RequestNumber\":\"TRI63893763867093166000\",\"Index Name\":\"Nifty Non-Cyclical Consumer\",\"Date\":\"04 Apr 2005\",\"TotalReturnsIndex\":\"999.40\"},{\"RequestNumber\":\"TRI63893763867093166000\",\"Index Name\":\"Nifty Non-Cyclical Consumer\",\"Date\":\"01 Apr 2005\",\"TotalReturnsIndex\":\"1000.00\"}]"
}